dist_s1_enumerator/__init__.py
dist_s1_enumerator/asf.py
dist_s1_enumerator/constants.py
dist_s1_enumerator/dist_enum.py
dist_s1_enumerator/dist_enum_inputs.py
dist_s1_enumerator/exceptions.py
dist_s1_enumerator/mgrs_burst_data.py
dist_s1_enumerator/param_models.py
dist_s1_enumerator/py.typed
dist_s1_enumerator/rtc_s1_io.py
dist_s1_enumerator/tabular_models.py
dist_s1_enumerator/data/jpl_burst_geo.parquet
dist_s1_enumerator/data/mgrs.parquet
dist_s1_enumerator/data/mgrs_burst_lookup_table.parquet
dist_s1_enumerator-1.0.11.dist-info/licenses/LICENSE
dist_s1_enumerator-1.0.11.dist-info/METADATA
dist_s1_enumerator-1.0.11.dist-info/WHEEL
dist_s1_enumerator-1.0.11.dist-info/top_level.txt
dist_s1_enumerator-1.0.11.dist-info/RECORD
