Metadata-Version: 2.4
Name: dist-s1-enumerator
Version: 1.0.11
Summary: Enumeration and ops library for the OPERA DIST-S1 project
Author-email: "Richard West, Charlie Marshak, Talib Oliver-Cabrera, and Jungkyo Jung" <charlie.z.marshak@jpl.nasa.gov>
License: Apache-2.0
Project-URL: Homepage, https://github.com/opera-adt/dist-s1-enumerator
Project-URL: Bug Tracker, https://github.com/opera-adt/dist-s1-enumerator/issues
Project-URL: Discussions, https://github.com/opera-adt/dist-s1-enumerator/discussions
Project-URL: Changelog, https://github.com/opera-adt/dist-s1-enumerator/releases
Classifier: Intended Audience :: Developers
Classifier: Intended Audience :: Science/Research
Classifier: Programming Language :: Python :: 3
Classifier: Programming Language :: Python :: 3.12
Classifier: Programming Language :: Python :: 3.13
Classifier: Programming Language :: Python
Classifier: Topic :: Scientific/Engineering
Requires-Python: >=3.12
License-File: LICENSE
Requires-Dist: numpy
Dynamic: license-file
